{
    "property_types": [
        {
            "id": 0,
            "name": "Apartamento"
        },
        {
            "id": 1,
            "name": "Local Comercial"
        },
        {
            "id": 2,
            "name": "Local"
        },
        {
            "id": 3,
            "name": "Oficina"
        },
        {
            "id": 4,
            "name": "Casa"
        },
        {
            "id": 5,
            "name": "Terreno"
        },
        {
            "id": 6,
            "name": "Campo"
        },
        {
            "id": 7,
            "name": "Garage"
        },
        {
            "id": 8,
            "name": "Cochera"
        },
        {
            "id": 9,
            "name": "Otro"
        }
    ]
}